LICENSE
MANIFEST.in
README.md
setup.py
django_keybase_verification.egg-info/PKG-INFO
django_keybase_verification.egg-info/SOURCES.txt
django_keybase_verification.egg-info/dependency_links.txt
django_keybase_verification.egg-info/top_level.txt
keybase_verification/__init__.py
keybase_verification/admin.py
keybase_verification/apps.py
keybase_verification/models.py
keybase_verification/tests.py
keybase_verification/urls.py
keybase_verification/views.py
keybase_verification/migrations/0001_initial.py
keybase_verification/migrations/0002_auto_20170221_1310.py
keybase_verification/migrations/__init__.py