Metadata-Version: 1.1
Name: django-keybase-verification
Version: 1.1.0
Summary: A simple Django app to make Keybase.io verification easy.
Home-page: https://github.com/bsquidwrd/django-keybase-verification
Author: bsquidwrd
Author-email: pypi@bsquidwrd.com
License: MIT License
Platform: UNKNOWN
Classifier: Environment :: Web Environment
Classifier: Framework :: Django
Classifier: Intended Audience :: Developers
Classifier: License :: OSI Approved :: MIT License
Classifier: Operating System :: OS Independent
Classifier: Programming Language :: Python
Classifier: Programming Language :: Python :: 3.5
Classifier: Programming Language :: Python :: 3.6
Classifier: Topic :: Internet :: WWW/HTTP
Classifier: Topic :: Internet :: WWW/HTTP :: Dynamic Content
